[{"@context":"http:\/\/schema.org","@graph":[{"@type":"Person","name":"Jimmy Cabra-Garc\u00eda","image":{"@type":"ImageObject","contentUrl":"https:\/\/i1.rgstatic.net\/ii\/profile.image\/455336399249409-1485572065625_Q128\/Jimmy-Cabra-Garcia.jpg"},"mainEntityOfPage":"https:\/\/www.researchgate.net\/profile\/Jimmy-Cabra-Garcia","url":"https:\/\/www.researchgate.net\/profile\/Jimmy-Cabra-Garcia","sameAs":"https:\/\/www.researchgate.net\/profile\/Jimmy-Cabra-Garcia","jobTitle":"Professor","affiliation":{"@type":"Organization","name":"Universidad del Valle (Colombia)","url":"https:\/\/www.researchgate.net\/institution\/Universidad-del-Valle-Colombia"}},{"@type":"WebPage","url":"https:\/\/www.researchgate.net\/profile\/Jimmy-Cabra-Garcia","reviewedBy":{"@type":"Person","name":"Jimmy Cabra-Garc\u00eda"}}]},{"@context":"http:\/\/schema.org","@type":"BreadcrumbList","itemListElement":[{"@type":"ListItem","position":1,"item":{"@id":"https:\/\/www.researchgate.net\/","name":"Home"}},{"@type":"ListItem","position":2,"item":{"@id":"https:\/\/www.researchgate.net\/institution\/Universidad-del-Valle-Colombia","name":"Universidad del Valle (Colombia)"}},{"@type":"ListItem","position":3,"item":{"@id":"https:\/\/www.researchgate.net\/profile\/Jimmy-Cabra-Garcia","name":"Jimmy Cabra-Garc\u00eda"}}]}]